cprotobuf/__init__.py
cprotobuf/internal.cpython-312-darwin.so
cprotobuf/plugin_pb.py
klar_cprotobuf-0.0.1.data/scripts/protoc-gen-cprotobuf
klar_cprotobuf-0.0.1.dist-info/LICENSE
klar_cprotobuf-0.0.1.dist-info/METADATA
klar_cprotobuf-0.0.1.dist-info/WHEEL
klar_cprotobuf-0.0.1.dist-info/top_level.txt
klar_cprotobuf-0.0.1.dist-info/RECORD
