Metadata-Version: 2.1
Name: klar-cprotobuf
Version: 0.0.1
Summary: pythonic and high performance protocol buffer implementation.
Home-page: https://github.com/klar/cprotobuf
Author: klar
Author-email: klar@gmail.com
License: MIT
Classifier: Programming Language :: Python :: 3
Classifier: Programming Language :: Python :: 3.12
License-File: LICENSE
